{
  "order": [
    "555810167",
    "2480288608",
    "3496353835",
    "3502646048",
    "937264051",
    "303072207",
    "301180100",
    "303250733",
    "3006481843",
    "555788439",
    "301182153",
    "3518397690",
    "2642163763",
    "303084032",
    "3012526977",
    "462726209",
    "3452089453",
    "3012603492",
    "303044923",
    "3529006964",
    "3488149620",
    "1419152395",
    "2477536391",
    "1419154382",
    "3486966273",
    "303078068",
    "3529157347",
    "3517384759",
    "13667589868",
    "3423119867",
    "13767380828",
    "3481714423",
    "383930926",
    "3019466201",
    "3186972787",
    "13643548312",
    "3604403076",
    "3555172406",
    "2418772568",
    "13749029773"
  ],
  "items": {
    "555810167": {
      "key": "555810167",
      "category_name": "Chilled Desserts",
      "category_url": "https://www.lazada.sg/catalog?q=Chilled%20Desserts&from=hp_categories&src=all_channel",
      "product_url": "https://www.lazada.sg/products/pdp-i555810167.html",
      "title": "",
      "image_url": "",
      "source_page": "https://www.lazada.sg/catalog?q=Chilled%20Desserts&from=hp_categories&src=all_channel",
      "detail_status": "pending"
    },
    "2480288608": {
      "key": "2480288608",
      "category_name": "Chilled Desserts",
      "category_url": "https://www.lazada.sg/catalog?q=Chilled%20Desserts&from=hp_categories&src=all_channel",
      "product_url": "https://www.lazada.sg/products/pdp-i2480288608.html",
      "title": "",
      "image_url": "",
      "source_page": "https://www.lazada.sg/catalog?q=Chilled%20Desserts&from=hp_categories&src=all_channel",
      "detail_status": "pending"
    },
    "3496353835": {
      "key": "3496353835",
      "category_name": "Chilled Desserts",
      "category_url": "https://www.lazada.sg/catalog?q=Chilled%20Desserts&from=hp_categories&src=all_channel",
      "product_url": "https://www.lazada.sg/products/pdp-i3496353835.html",
      "title": "",
      "image_url": "",
      "source_page": "https://www.lazada.sg/catalog?q=Chilled%20Desserts&from=hp_categories&src=all_channel",
      "detail_status": "pending"
    },
    "3502646048": {
      "key": "3502646048",
      "category_name": "Chilled Desserts",
      "category_url": "https://www.lazada.sg/catalog?q=Chilled%20Desserts&from=hp_categories&src=all_channel",
      "product_url": "https://www.lazada.sg/products/pdp-i3502646048.html",
      "title": "",
      "image_url": "",
      "source_page": "https://www.lazada.sg/catalog?q=Chilled%20Desserts&from=hp_categories&src=all_channel",
      "detail_status": "pending"
    },
    "937264051": {
      "key": "937264051",
      "category_name": "Chilled Desserts",
      "category_url": "https://www.lazada.sg/catalog?q=Chilled%20Desserts&from=hp_categories&src=all_channel",
      "product_url": "https://www.lazada.sg/products/pdp-i937264051.html",
      "title": "",
      "image_url": "",
      "source_page": "https://www.lazada.sg/catalog?q=Chilled%20Desserts&from=hp_categories&src=all_channel",
      "detail_status": "pending"
    },
    "303072207": {
      "key": "303072207",
      "category_name": "Chilled Desserts",
      "category_url": "https://www.lazada.sg/catalog?q=Chilled%20Desserts&from=hp_categories&src=all_channel",
      "product_url": "https://www.lazada.sg/products/pdp-i303072207.html",
      "title": "",
      "image_url": "",
      "source_page": "https://www.lazada.sg/catalog?q=Chilled%20Desserts&from=hp_categories&src=all_channel",
      "detail_status": "pending"
    },
    "301180100": {
      "key": "301180100",
      "category_name": "Chilled Desserts",
      "category_url": "https://www.lazada.sg/catalog?q=Chilled%20Desserts&from=hp_categories&src=all_channel",
      "product_url": "https://www.lazada.sg/products/pdp-i301180100.html",
      "title": "",
      "image_url": "",
      "source_page": "https://www.lazada.sg/catalog?q=Chilled%20Desserts&from=hp_categories&src=all_channel",
      "detail_status": "pending"
    },
    "303250733": {
      "key": "303250733",
      "category_name": "Chilled Desserts",
      "category_url": "https://www.lazada.sg/catalog?q=Chilled%20Desserts&from=hp_categories&src=all_channel",
      "product_url": "https://www.lazada.sg/products/pdp-i303250733.html",
      "title": "",
      "image_url": "",
      "source_page": "https://www.lazada.sg/catalog?q=Chilled%20Desserts&from=hp_categories&src=all_channel",
      "detail_status": "pending"
    },
    "3006481843": {
      "key": "3006481843",
      "category_name": "Chilled Desserts",
      "category_url": "https://www.lazada.sg/catalog?q=Chilled%20Desserts&from=hp_categories&src=all_channel",
      "product_url": "https://www.lazada.sg/products/pdp-i3006481843.html",
      "title": "",
      "image_url": "",
      "source_page": "https://www.lazada.sg/catalog?q=Chilled%20Desserts&from=hp_categories&src=all_channel",
      "detail_status": "pending"
    },
    "555788439": {
      "key": "555788439",
      "category_name": "Chilled Desserts",
      "category_url": "https://www.lazada.sg/catalog?q=Chilled%20Desserts&from=hp_categories&src=all_channel",
      "product_url": "https://www.lazada.sg/products/pdp-i555788439.html",
      "title": "",
      "image_url": "",
      "source_page": "https://www.lazada.sg/catalog?q=Chilled%20Desserts&from=hp_categories&src=all_channel",
      "detail_status": "pending"
    },
    "301182153": {
      "key": "301182153",
      "category_name": "Chilled Desserts",
      "category_url": "https://www.lazada.sg/catalog?q=Chilled%20Desserts&from=hp_categories&src=all_channel",
      "product_url": "https://www.lazada.sg/products/pdp-i301182153.html",
      "title": "",
      "image_url": "",
      "source_page": "https://www.lazada.sg/catalog?q=Chilled%20Desserts&from=hp_categories&src=all_channel",
      "detail_status": "pending"
    },
    "3518397690": {
      "key": "3518397690",
      "category_name": "Chilled Desserts",
      "category_url": "https://www.lazada.sg/catalog?q=Chilled%20Desserts&from=hp_categories&src=all_channel",
      "product_url": "https://www.lazada.sg/products/pdp-i3518397690.html",
      "title": "",
      "image_url": "",
      "source_page": "https://www.lazada.sg/catalog?q=Chilled%20Desserts&from=hp_categories&src=all_channel",
      "detail_status": "pending"
    },
    "2642163763": {
      "key": "2642163763",
      "category_name": "Chilled Desserts",
      "category_url": "https://www.lazada.sg/catalog?q=Chilled%20Desserts&from=hp_categories&src=all_channel",
      "product_url": "https://www.lazada.sg/products/pdp-i2642163763.html",
      "title": "",
      "image_url": "",
      "source_page": "https://www.lazada.sg/catalog?q=Chilled%20Desserts&from=hp_categories&src=all_channel",
      "detail_status": "pending"
    },
    "303084032": {
      "key": "303084032",
      "category_name": "Chilled Desserts",
      "category_url": "https://www.lazada.sg/catalog?q=Chilled%20Desserts&from=hp_categories&src=all_channel",
      "product_url": "https://www.lazada.sg/products/pdp-i303084032.html",
      "title": "",
      "image_url": "",
      "source_page": "https://www.lazada.sg/catalog?q=Chilled%20Desserts&from=hp_categories&src=all_channel",
      "detail_status": "pending"
    },
    "3012526977": {
      "key": "3012526977",
      "category_name": "Chilled Desserts",
      "category_url": "https://www.lazada.sg/catalog?q=Chilled%20Desserts&from=hp_categories&src=all_channel",
      "product_url": "https://www.lazada.sg/products/pdp-i3012526977.html",
      "title": "",
      "image_url": "",
      "source_page": "https://www.lazada.sg/catalog?q=Chilled%20Desserts&from=hp_categories&src=all_channel",
      "detail_status": "pending"
    },
    "462726209": {
      "key": "462726209",
      "category_name": "Chilled Desserts",
      "category_url": "https://www.lazada.sg/catalog?q=Chilled%20Desserts&from=hp_categories&src=all_channel",
      "product_url": "https://www.lazada.sg/products/pdp-i462726209.html",
      "title": "",
      "image_url": "",
      "source_page": "https://www.lazada.sg/catalog?q=Chilled%20Desserts&from=hp_categories&src=all_channel",
      "detail_status": "pending"
    },
    "3452089453": {
      "key": "3452089453",
      "category_name": "Chilled Desserts",
      "category_url": "https://www.lazada.sg/catalog?q=Chilled%20Desserts&from=hp_categories&src=all_channel",
      "product_url": "https://www.lazada.sg/products/pdp-i3452089453.html",
      "title": "",
      "image_url": "",
      "source_page": "https://www.lazada.sg/catalog?q=Chilled%20Desserts&from=hp_categories&src=all_channel",
      "detail_status": "pending"
    },
    "3012603492": {
      "key": "3012603492",
      "category_name": "Chilled Desserts",
      "category_url": "https://www.lazada.sg/catalog?q=Chilled%20Desserts&from=hp_categories&src=all_channel",
      "product_url": "https://www.lazada.sg/products/pdp-i3012603492.html",
      "title": "",
      "image_url": "",
      "source_page": "https://www.lazada.sg/catalog?q=Chilled%20Desserts&from=hp_categories&src=all_channel",
      "detail_status": "pending"
    },
    "303044923": {
      "key": "303044923",
      "category_name": "Chilled Desserts",
      "category_url": "https://www.lazada.sg/catalog?q=Chilled%20Desserts&from=hp_categories&src=all_channel",
      "product_url": "https://www.lazada.sg/products/pdp-i303044923.html",
      "title": "",
      "image_url": "",
      "source_page": "https://www.lazada.sg/catalog?q=Chilled%20Desserts&from=hp_categories&src=all_channel",
      "detail_status": "pending"
    },
    "3529006964": {
      "key": "3529006964",
      "category_name": "Chilled Desserts",
      "category_url": "https://www.lazada.sg/catalog?q=Chilled%20Desserts&from=hp_categories&src=all_channel",
      "product_url": "https://www.lazada.sg/products/pdp-i3529006964.html",
      "title": "",
      "image_url": "",
      "source_page": "https://www.lazada.sg/catalog?q=Chilled%20Desserts&from=hp_categories&src=all_channel",
      "detail_status": "pending"
    },
    "3488149620": {
      "key": "3488149620",
      "category_name": "Chilled Desserts",
      "category_url": "https://www.lazada.sg/catalog?q=Chilled%20Desserts&from=hp_categories&src=all_channel",
      "product_url": "https://www.lazada.sg/products/pdp-i3488149620.html",
      "title": "",
      "image_url": "",
      "source_page": "https://www.lazada.sg/catalog?q=Chilled%20Desserts&from=hp_categories&src=all_channel",
      "detail_status": "pending"
    },
    "1419152395": {
      "key": "1419152395",
      "category_name": "Chilled Desserts",
      "category_url": "https://www.lazada.sg/catalog?q=Chilled%20Desserts&from=hp_categories&src=all_channel",
      "product_url": "https://www.lazada.sg/products/pdp-i1419152395.html",
      "title": "",
      "image_url": "",
      "source_page": "https://www.lazada.sg/catalog?q=Chilled%20Desserts&from=hp_categories&src=all_channel",
      "detail_status": "pending"
    },
    "2477536391": {
      "key": "2477536391",
      "category_name": "Chilled Desserts",
      "category_url": "https://www.lazada.sg/catalog?q=Chilled%20Desserts&from=hp_categories&src=all_channel",
      "product_url": "https://www.lazada.sg/products/pdp-i2477536391.html",
      "title": "",
      "image_url": "",
      "source_page": "https://www.lazada.sg/catalog?q=Chilled%20Desserts&from=hp_categories&src=all_channel",
      "detail_status": "pending"
    },
    "1419154382": {
      "key": "1419154382",
      "category_name": "Chilled Desserts",
      "category_url": "https://www.lazada.sg/catalog?q=Chilled%20Desserts&from=hp_categories&src=all_channel",
      "product_url": "https://www.lazada.sg/products/pdp-i1419154382.html",
      "title": "",
      "image_url": "",
      "source_page": "https://www.lazada.sg/catalog?q=Chilled%20Desserts&from=hp_categories&src=all_channel",
      "detail_status": "pending"
    },
    "3486966273": {
      "key": "3486966273",
      "category_name": "Chilled Desserts",
      "category_url": "https://www.lazada.sg/catalog?q=Chilled%20Desserts&from=hp_categories&src=all_channel",
      "product_url": "https://www.lazada.sg/products/pdp-i3486966273.html",
      "title": "",
      "image_url": "",
      "source_page": "https://www.lazada.sg/catalog?q=Chilled%20Desserts&from=hp_categories&src=all_channel",
      "detail_status": "pending"
    },
    "303078068": {
      "key": "303078068",
      "category_name": "Chilled Desserts",
      "category_url": "https://www.lazada.sg/catalog?q=Chilled%20Desserts&from=hp_categories&src=all_channel",
      "product_url": "https://www.lazada.sg/products/pdp-i303078068.html",
      "title": "",
      "image_url": "",
      "source_page": "https://www.lazada.sg/catalog?q=Chilled%20Desserts&from=hp_categories&src=all_channel",
      "detail_status": "pending"
    },
    "3529157347": {
      "key": "3529157347",
      "category_name": "Chilled Desserts",
      "category_url": "https://www.lazada.sg/catalog?q=Chilled%20Desserts&from=hp_categories&src=all_channel",
      "product_url": "https://www.lazada.sg/products/pdp-i3529157347.html",
      "title": "",
      "image_url": "",
      "source_page": "https://www.lazada.sg/catalog?q=Chilled%20Desserts&from=hp_categories&src=all_channel",
      "detail_status": "pending"
    },
    "3517384759": {
      "key": "3517384759",
      "category_name": "Chilled Desserts",
      "category_url": "https://www.lazada.sg/catalog?q=Chilled%20Desserts&from=hp_categories&src=all_channel",
      "product_url": "https://www.lazada.sg/products/pdp-i3517384759.html",
      "title": "",
      "image_url": "",
      "source_page": "https://www.lazada.sg/catalog?q=Chilled%20Desserts&from=hp_categories&src=all_channel",
      "detail_status": "pending"
    },
    "13667589868": {
      "key": "13667589868",
      "category_name": "Chilled Desserts",
      "category_url": "https://www.lazada.sg/catalog?q=Chilled%20Desserts&from=hp_categories&src=all_channel",
      "product_url": "https://www.lazada.sg/products/pdp-i13667589868.html",
      "title": "",
      "image_url": "",
      "source_page": "https://www.lazada.sg/catalog?q=Chilled%20Desserts&from=hp_categories&src=all_channel",
      "detail_status": "pending"
    },
    "3423119867": {
      "key": "3423119867",
      "category_name": "Chilled Desserts",
      "category_url": "https://www.lazada.sg/catalog?q=Chilled%20Desserts&from=hp_categories&src=all_channel",
      "product_url": "https://www.lazada.sg/products/pdp-i3423119867.html",
      "title": "",
      "image_url": "",
      "source_page": "https://www.lazada.sg/catalog?q=Chilled%20Desserts&from=hp_categories&src=all_channel",
      "detail_status": "pending"
    },
    "13767380828": {
      "key": "13767380828",
      "category_name": "Chilled Desserts",
      "category_url": "https://www.lazada.sg/catalog?q=Chilled%20Desserts&from=hp_categories&src=all_channel",
      "product_url": "https://www.lazada.sg/products/pdp-i13767380828.html",
      "title": "",
      "image_url": "",
      "source_page": "https://www.lazada.sg/catalog?q=Chilled%20Desserts&from=hp_categories&src=all_channel",
      "detail_status": "pending"
    },
    "3481714423": {
      "key": "3481714423",
      "category_name": "Chilled Desserts",
      "category_url": "https://www.lazada.sg/catalog?q=Chilled%20Desserts&from=hp_categories&src=all_channel",
      "product_url": "https://www.lazada.sg/products/pdp-i3481714423.html",
      "title": "",
      "image_url": "",
      "source_page": "https://www.lazada.sg/catalog?q=Chilled%20Desserts&from=hp_categories&src=all_channel",
      "detail_status": "pending"
    },
    "383930926": {
      "key": "383930926",
      "category_name": "Chilled Desserts",
      "category_url": "https://www.lazada.sg/catalog?q=Chilled%20Desserts&from=hp_categories&src=all_channel",
      "product_url": "https://www.lazada.sg/products/pdp-i383930926.html",
      "title": "",
      "image_url": "",
      "source_page": "https://www.lazada.sg/catalog?q=Chilled%20Desserts&from=hp_categories&src=all_channel",
      "detail_status": "pending"
    },
    "3019466201": {
      "key": "3019466201",
      "category_name": "Chilled Desserts",
      "category_url": "https://www.lazada.sg/catalog?q=Chilled%20Desserts&from=hp_categories&src=all_channel",
      "product_url": "https://www.lazada.sg/products/pdp-i3019466201.html",
      "title": "",
      "image_url": "",
      "source_page": "https://www.lazada.sg/catalog?q=Chilled%20Desserts&from=hp_categories&src=all_channel",
      "detail_status": "pending"
    },
    "3186972787": {
      "key": "3186972787",
      "category_name": "Chilled Desserts",
      "category_url": "https://www.lazada.sg/catalog?q=Chilled%20Desserts&from=hp_categories&src=all_channel",
      "product_url": "https://www.lazada.sg/products/pdp-i3186972787.html",
      "title": "",
      "image_url": "",
      "source_page": "https://www.lazada.sg/catalog?q=Chilled%20Desserts&from=hp_categories&src=all_channel",
      "detail_status": "pending"
    },
    "13643548312": {
      "key": "13643548312",
      "category_name": "Chilled Desserts",
      "category_url": "https://www.lazada.sg/catalog?q=Chilled%20Desserts&from=hp_categories&src=all_channel",
      "product_url": "https://www.lazada.sg/products/pdp-i13643548312.html",
      "title": "",
      "image_url": "",
      "source_page": "https://www.lazada.sg/catalog?q=Chilled%20Desserts&from=hp_categories&src=all_channel",
      "detail_status": "pending"
    },
    "3604403076": {
      "key": "3604403076",
      "category_name": "Chilled Desserts",
      "category_url": "https://www.lazada.sg/catalog?q=Chilled%20Desserts&from=hp_categories&src=all_channel",
      "product_url": "https://www.lazada.sg/products/pdp-i3604403076.html",
      "title": "",
      "image_url": "",
      "source_page": "https://www.lazada.sg/catalog?q=Chilled%20Desserts&from=hp_categories&src=all_channel",
      "detail_status": "pending"
    },
    "3555172406": {
      "key": "3555172406",
      "category_name": "Chilled Desserts",
      "category_url": "https://www.lazada.sg/catalog?q=Chilled%20Desserts&from=hp_categories&src=all_channel",
      "product_url": "https://www.lazada.sg/products/pdp-i3555172406.html",
      "title": "",
      "image_url": "",
      "source_page": "https://www.lazada.sg/catalog?q=Chilled%20Desserts&from=hp_categories&src=all_channel",
      "detail_status": "pending"
    },
    "2418772568": {
      "key": "2418772568",
      "category_name": "Chilled Desserts",
      "category_url": "https://www.lazada.sg/catalog?q=Chilled%20Desserts&from=hp_categories&src=all_channel",
      "product_url": "https://www.lazada.sg/products/pdp-i2418772568.html",
      "title": "",
      "image_url": "",
      "source_page": "https://www.lazada.sg/catalog?q=Chilled%20Desserts&from=hp_categories&src=all_channel",
      "detail_status": "pending"
    },
    "13749029773": {
      "key": "13749029773",
      "category_name": "Chilled Desserts",
      "category_url": "https://www.lazada.sg/catalog?q=Chilled%20Desserts&from=hp_categories&src=all_channel",
      "product_url": "https://www.lazada.sg/products/pdp-i13749029773.html",
      "title": "",
      "image_url": "",
      "source_page": "https://www.lazada.sg/catalog?q=Chilled%20Desserts&from=hp_categories&src=all_channel",
      "detail_status": "pending"
    }
  }
}